requestsRenderJs/TechsunRequests.py
requestsRenderJs/__init__.py
requestsRenderJs-0.0.4.dist-info/METADATA
requestsRenderJs-0.0.4.dist-info/WHEEL
requestsRenderJs-0.0.4.dist-info/top_level.txt
requestsRenderJs-0.0.4.dist-info/RECORD
